{"name": "Common Ancestor", "node_score": "9.0", "children": [{"name": "HPGPNRMPCCSOTSJMCMMRHCCOOOSVCTOPBOCECFCMAOLPPEMMESC", "node_score": "9.0", "branch_score": "null", "children": [{"name": "HPGPNRMPCCSOTSJMCMMRHCCOOO", "node_score": "9.0", "branch_score": "null", "children": [{"name": "HPGPNRMPCCSOT", "node_score": "9.0", "branch_score": "null", "children": [{"name": "HPGPNRMPCCSO", "node_score": "9.0", "branch_score": "null", "children": [{"name": "HPGPNRMPCCS", "node_score": "9.0", "branch_score": "null", "children": [{"name": "HPGPNRMPC", "node_score": "0.1", "branch_score": "null", "children": [{"name": "HPGPN", "node_score": "0.1", "branch_score": 1.0, "children": [{"name": "HPGP", "node_score": "0.1", "branch_score": 0.0, "children": [{"name": "HPG", "node_score": "0.1", "branch_score": 0.18658065564852427, "children": [{"name": "HP", "node_score": "0.1", "branch_score": 0.0, "children": [{"name": "Human", "node_score": "0.1", "branch_score": 0.17033479320820016}, {"name": "Chimp", "node_score": "0.1", "branch_score": 0.39283600141812447}]}, {"name": "Gorilla", "node_score": "0.1", "branch_score": 0.39283600141812447}]}, {"name": "Orangutan", "node_score": "0.1", "branch_score": 0.4368292053736753}]}, {"name": "Gibbon", "node_score": "0.1", "branch_score": 1.0}]}, {"name": "RMPC", "node_score": "0.1", "branch_score": 0.6586831610768039, "children": [{"name": "RMP", "node_score": "0.1", "branch_score": 0.0, "children": [{"name": "RM", "node_score": "0.1", "branch_score": 0.2614030824062446, "children": [{"name": "Rhesus macaque", "node_score": "0.1", "branch_score": 0.30176771222008003}, {"name": "Crab eating macaque", "node_score": "0.1", "branch_score": "null"}]}, {"name": "Olive Baboon", "node_score": "0.1", "branch_score": 0.0}]}, {"name": "Green monkey", "node_score": "9.0", "branch_score": "null"}]}]}, {"name": "CS", "node_score": "9.0", "branch_score": "null", "children": [{"name": "Marmoset", "node_score": "9.0", "branch_score": "null"}, {"name": "Squirrel monkey", "node_score": "9.0", "branch_score": "null"}]}]}, {"name": "Bushbaby", "node_score": "9.0", "branch_score": "null"}]}, {"name": "Chinese tree shrew", "node_score": "9.0", "branch_score": "null"}]}, {"name": "SJMCMMRHCCOOO", "node_score": "9.0", "branch_score": "null", "children": [{"name": "SJMCMMRHCCO", "node_score": "9.0", "branch_score": 0.0, "children": [{"name": "SJMCMMR", "node_score": "9.0", "branch_score": 0.0, "children": [{"name": "Squirrel", "node_score": "9.0", "branch_score": 0.0}, {"name": "JMCMMR", "node_score": "9.0", "branch_score": 0.0, "children": [{"name": "Lesser Egyptian jerboa", "node_score": "9.0", "branch_score": 0.0}, {"name": "MCMMR", "node_score": "9.0", "branch_score": 0.0, "children": [{"name": "MCM", "node_score": "9.0", "branch_score": 0.0, "children": [{"name": "Prairie vole", "node_score": "9.0", "branch_score": 0.0}, {"name": "CM", "node_score": "9.0", "branch_score": 0.0, "children": [{"name": "Chinese hamster", "node_score": "9.0", "branch_score": 0.0}, {"name": "Golden hamster", "node_score": "9.0", "branch_score": 0.0}]}]}, {"name": "MR", "node_score": "9.0", "branch_score": 0.0, "children": [{"name": "Mouse", "node_score": "9.0", "branch_score": 0.03659200349886014}, {"name": "Rat", "node_score": "9.0", "branch_score": 0.0}]}]}]}]}, {"name": "HCCO", "node_score": "9.0", "branch_score": 0.0, "children": [{"name": "Naked mole rat", "node_score": "9.0", "branch_score": 0.0}, {"name": "CCO", "node_score": "9.0", "branch_score": 0.0, "children": [{"name": "CO", "node_score": "9.0", "branch_score": 0.0, "children": [{"name": "Chinchilla", "node_score": "9.0", "branch_score": 0.08512711562734608}, {"name": "Brush tailed rat", "node_score": "9.0", "branch_score": 0.0}]}, {"name": "Guinea pig", "node_score": "9.0", "branch_score": 0.0}]}]}]}, {"name": "OO", "node_score": "9.0", "branch_score": 0.0, "children": [{"name": "Pika", "node_score": "9.0", "branch_score": 0.0}, {"name": "Rabbit", "node_score": "9.0", "branch_score": 0.0}]}]}]}, {"name": "SVCTOPBOCECFCMAOLPPEMMESC", "node_score": "9.0", "branch_score": "null", "children": [{"name": "SVCTOPBOCECFCMAOLPPEMM", "node_score": "9.0", "branch_score": "null", "children": [{"name": "SVCTOPBOC", "node_score": "9.0", "branch_score": "null", "children": [{"name": "Pig", "node_score": "9.0", "branch_score": "null"}, {"name": "VCTOPBOC", "node_score": "9.0", "branch_score": "null", "children": [{"name": "VC", "node_score": "9.0", "branch_score": "null", "children": [{"name": "Alpaca", "node_score": "9.0", "branch_score": 0.0}, {"name": "Bactrian camel", "node_score": "9.0", "branch_score": 0.05220616555127626}]}, {"name": "TOPBOC", "node_score": "9.0", "branch_score": "null", "children": [{"name": "TO", "node_score": "9.0", "branch_score": "null", "children": [{"name": "Dolphin", "node_score": "9.0", "branch_score": 0.05085000672393856}, {"name": "Killer whale", "node_score": "9.0", "branch_score": 0.05085000672393856}]}, {"name": "PBOC", "node_score": "9.0", "branch_score": "null", "children": [{"name": "Tibetan antelope", "node_score": "9.0", "branch_score": 0.0}, {"name": "BOC", "node_score": "9.0", "branch_score": 0.0, "children": [{"name": "Cow", "node_score": "9.0", "branch_score": 0.0}, {"name": "OC", "node_score": "9.0", "branch_score": 0.0, "children": [{"name": "Sheep", "node_score": "9.0", "branch_score": 0.0}, {"name": "Domestic goat", "node_score": "9.0", "branch_score": 0.0}]}]}]}]}]}]}, {"name": "ECFCMAOLPPEMM", "node_score": "9.0", "branch_score": "null", "children": [{"name": "ECFCMAOL", "node_score": "9.0", "branch_score": "null", "children": [{"name": "EC", "node_score": "9.0", "branch_score": "null", "children": [{"name": "Horse", "node_score": "9.0", "branch_score": 0.06215173405068723}, {"name": "White rhinoceros", "node_score": "9.0", "branch_score": 0.06215173405068723}]}, {"name": "FCMAOL", "node_score": "9.0", "branch_score": "null", "children": [{"name": "Cat", "node_score": "9.0", "branch_score": "null"}, {"name": "CMAOL", "node_score": "9.0", "branch_score": "null", "children": [{"name": "Dog", "node_score": "9.0", "branch_score": "null"}, {"name": "MAOL", "node_score": "9.0", "branch_score": "null", "children": [{"name": "Ferret", "node_score": "9.0", "branch_score": 0.058440614097613815}, {"name": "AOL", "node_score": "9.0", "branch_score": 0.0, "children": [{"name": "Giant panda", "node_score": "9.0", "branch_score": 0.058440614097613815}, {"name": "OL", "node_score": "9.0", "branch_score": 0.0, "children": [{"name": "Pacific walrus", "node_score": "9.0", "branch_score": 0.05085000672393856}, {"name": "Weddell seal", "node_score": "9.0", "branch_score": 0.05085000672393856}]}]}]}]}]}]}, {"name": "PPEMM", "node_score": "9.0", "branch_score": "null", "children": [{"name": "PP", "node_score": "9.0", "branch_score": 0.0, "children": [{"name": "Black flying fox", "node_score": "9.0", "branch_score": 0.049562525461502874}, {"name": "Megabat", "node_score": "9.0", "branch_score": 0.0}]}, {"name": "EMM", "node_score": "9.0", "branch_score": 0.0, "children": [{"name": "Big brown bat", "node_score": "9.0", "branch_score": 0.0}, {"name": "MM", "node_score": "9.0", "branch_score": 0.0, "children": [{"name": "David's myotis", "node_score": "9.0", "branch_score": 0.0}, {"name": "Microbat", "node_score": "9.0", "branch_score": 0.03527330005460476}]}]}]}]}]}, {"name": "ESC", "node_score": "9.0", "branch_score": "null", "children": [{"name": "Hedgehog", "node_score": "9.0", "branch_score": 0.0}, {"name": "SC", "node_score": "9.0", "branch_score": 0.0, "children": [{"name": "Shrew", "node_score": "9.0", "branch_score": 0.0}, {"name": "Star-nosed mole", "node_score": "9.0", "branch_score": 0.0}]}]}]}]}, {"name": "LETCEOD", "node_score": "9.0", "branch_score": 0.0, "children": [{"name": "LETCEO", "node_score": "9.0", "branch_score": 0.0, "children": [{"name": "LETCE", "node_score": "9.0", "branch_score": 0.0, "children": [{"name": "LET", "node_score": "9.0", "branch_score": 0.0, "children": [{"name": "LE", "node_score": "9.0", "branch_score": 0.0, "children": [{"name": "Elephant", "node_score": "9.0", "branch_score": 0.10305617227521498}, {"name": "Cape elephant shrew", "node_score": "9.0", "branch_score": 0.0}]}, {"name": "Manatee", "node_score": "9.0", "branch_score": 0.05220616555127626}]}, {"name": "CE", "node_score": "9.0", "branch_score": 0.0, "children": [{"name": "Cape golden mole", "node_score": "9.0", "branch_score": 0.0}, {"name": "Lesser hedgehog tenrec", "node_score": "9.0", "branch_score": 0.04302624162965581}]}]}, {"name": "Aardvark", "node_score": "9.0", "branch_score": 0.10878438466952735}]}, {"name": "Armadillo", "node_score": "9.0", "branch_score": 0.053636648032882976}]}]}
